milasdk/__init__.py
milasdk/api.py
milasdk/const.py
milasdk/exceptions.py
milasdk/auth/__init__.py
milasdk/auth/abstract_async_session.py
milasdk/auth/default_async_session.py
milasdk/auth/mila_oath2.py
milasdk/gql/__init__.py
milasdk/gql/enums.py
milasdk/gql/mila_schema.gql
milasdk/gql/queries.py
milasdk/gql/scalars.py
milasdk/gql/transport.py
milasdk/gql/types.py
milasdk-2026.1.3.dist-info/licenses/LICENSE
milasdk-2026.1.3.dist-info/METADATA
milasdk-2026.1.3.dist-info/WHEEL
milasdk-2026.1.3.dist-info/top_level.txt
milasdk-2026.1.3.dist-info/RECORD
