Metadata-Version: 2.4
Name: milasdk
Version: 2026.1.3
Summary: Python SDK for Mila Air Purifiers
Home-page: https://github.com/simbaja/milasdk
Author: Jack Simbach
Author-email: jack.simbach@gmail.com
License: MIT
Classifier: License :: OSI Approved :: MIT License
Classifier: Programming Language :: Python :: 3
Classifier: Programming Language :: Python :: 3.12
License-File: LICENSE
Requires-Dist: aiohttp
Requires-Dist: magicattr
Requires-Dist: gql<4
Requires-Dist: StrEnum
Requires-Dist: oauthlib
Requires-Dist: async_oauthlib
Requires-Dist: aiofiles
Dynamic: author
Dynamic: author-email
Dynamic: classifier
Dynamic: description
Dynamic: description-content-type
Dynamic: home-page
Dynamic: license
Dynamic: license-file
Dynamic: requires-dist
Dynamic: summary
